DreampixAILoworksDetect/__init__.py
DreampixAILoworksDetect/baseline.py
DreampixAILoworksDetect/se_inception.py
DreampixAILoworksDetect/se_module.py
DreampixAILoworksDetect/se_resnet.py
DreampixAILoworksDetect/works_identificationB.py
dreampixAILowworksB-1.0.4.dist-info/METADATA
dreampixAILowworksB-1.0.4.dist-info/WHEEL
dreampixAILowworksB-1.0.4.dist-info/top_level.txt
dreampixAILowworksB-1.0.4.dist-info/RECORD
